{
  "aor": 0.001597666666666667,
  "aqi": 0.014469851444444444,
  "bids_meta": {
    "EchoTime": 0.037,
    "EffectiveEchoSpacing": 0.0005800087233,
    "FlipAngle": 52,
    "PhaseEncodingDirection": "j-",
    "RepetitionTime": 3.07,
    "SliceTiming": [
      0,
      0.415,
      0.08250000002,
      0.5,
      0.165,
      0.5825,
      0.25,
      0.665,
      0.3325,
      0,
      0.415,
      0.08250000002,
      0.5,
      0.165,
      0.5825,
      0.25,
      0.665,
      0.3325,
      0,
      0.415,
      0.08250000002,
      0.5,
      0.165,
      0.5825,
      0.25,
      0.665,
      0.3325,
      0,
      0.415,
      0.08250000002,
      0.5,
      0.165,
      0.5825,
      0.25,
      0.665,
      0.3325,
      0,
      0.415,
      0.08250000002,
      0.5,
      0.165,
      0.5825,
      0.25,
      0.665,
      0.3325,
      0,
      0.415,
      0.08250000002,
      0.5,
      0.165,
      0.5825,
      0.25,
      0.665,
      0.3325,
      0,
      0.415,
      0.08250000002,
      0.5,
      0.165,
      0.5825,
      0.25,
      0.665,
      0.3325,
      0,
      0.415,
      0.08250000002,
      0.5,
      0.165,
      0.5825,
      0.25,
      0.665,
      0.3325
    ],
    "TaskName": "REPEAT01",
    "dataset": "ds002382",
    "modality": "bold",
    "subject_id": "60",
    "task_id": "REPEAT01"
  },
  "dummy_trs": 1,
  "dvars_nstd": 58.05652562994415,
  "dvars_std": 1.0493702430167597,
  "dvars_vstd": 2.076543390502792,
  "efc": 0.5314137727448978,
  "fber": 530.3922119140625,
  "fd_mean": 0.335260533665793,
  "fd_num": 139,
  "fd_perc": 77.22222222222223,
  "fwhm_avg": 2.510046666666667,
  "fwhm_x": 2.41508,
  "fwhm_y": 2.55905,
  "fwhm_z": 2.55601,
  "gcor": 0.00667462,
  "gsr_x": -0.0036537270061671734,
  "gsr_y": 0.06911394745111465,
  "provenance": {
    "md5sum": "3a54c82b4fd199376d8a166cbf7b7872",
    "settings": {
      "fd_thres": 0.2,
      "testing": false
    },
    "software": "mriqc",
    "version": "22.0.1",
    "webapi_port": null,
    "webapi_url": "https://mriqc.nimh.nih.gov/api/v1"
  },
  "size_t": 180,
  "size_x": 104,
  "size_y": 104,
  "size_z": 72,
  "snr": 2.131740415691397,
  "spacing_tr": 3.069999933242798,
  "spacing_x": 2.0,
  "spacing_y": 2.0,
  "spacing_z": 2.0,
  "summary_bg_k": 100.90852439051477,
  "summary_bg_mad": 111.4741610146859,
  "summary_bg_mean": 403.76837158203125,
  "summary_bg_median": 187.95138549804688,
  "summary_bg_n": 507560.0,
  "summary_bg_p05": 102.5455394744873,
  "summary_bg_p95": 1394.3136474609375,
  "summary_bg_stdv": 730.8904418945312,
  "summary_fg_k": 3.660312344457423,
  "summary_fg_mad": 1516.5049804423693,
  "summary_fg_mean": 4841.6162109375,
  "summary_fg_median": 4349.03125,
  "summary_fg_n": 170242.0,
  "summary_fg_p05": 2512.351708984375,
  "summary_fg_p95": 8828.442480468746,
  "summary_fg_stdv": 2040.125732421875,
  "tsnr": 22.561460494995117
}